nzrapi/__init__.py
nzrapi/__main__.py
nzrapi/app.py
nzrapi/cli.py
nzrapi/decorators.py
nzrapi/dependencies.py
nzrapi/exceptions.py
nzrapi/filters.py
nzrapi/middleware.py
nzrapi/middleware_abstractions.py
nzrapi/pagination.py
nzrapi/permissions.py
nzrapi/requests.py
nzrapi/responses.py
nzrapi/routing.py
nzrapi/schemas.py
nzrapi/security.py
nzrapi/serializers.py
nzrapi/services.py
nzrapi/settings.py
nzrapi/status.py
nzrapi/typing.py
nzrapi/validators.py
nzrapi/views.py
nzrapi/websockets.py
nzrapi/ai/__init__.py
nzrapi/ai/context.py
nzrapi/ai/models.py
nzrapi/ai/protocol.py
nzrapi/ai/registry.py
nzrapi/db/__init__.py
nzrapi/db/fields.py
nzrapi/db/manager.py
nzrapi/db/models.py
nzrapi/docs/MIGRATION_FROM_FASTAPI.md
nzrapi/examples/quick_start.py
nzrapi-1.0.1.dist-info/METADATA
nzrapi-1.0.1.dist-info/WHEEL
nzrapi-1.0.1.dist-info/entry_points.txt
nzrapi-1.0.1.dist-info/licenses/LICENSE
nzrapi-1.0.1.dist-info/RECORD
